nblint/__init__.py
nblint-0.0.3.data/scripts/nblint
nblint-0.0.3.data/scripts/nblint.cmd
nblint-0.0.3.dist-info/DESCRIPTION.rst
nblint-0.0.3.dist-info/METADATA
nblint-0.0.3.dist-info/RECORD
nblint-0.0.3.dist-info/WHEEL
nblint-0.0.3.dist-info/metadata.json
nblint-0.0.3.dist-info/top_level.txt
