Metadata-Version: 2.0
Name: nblint
Version: 0.0.3
Summary: Linting Jupyter notebooks
Home-page: http://github.com/alexandercbooth/nblint
Author: Alexander C. Booth
Author-email: UNKNOWN
License: MIT
Platform: UNKNOWN
Requires-Dist: flake8
Requires-Dist: nbformat
Requires-Dist: pycodestyle
